suplex/__init__.py
suplex/suplex.py
suplex-0.2.6.dist-info/METADATA
suplex-0.2.6.dist-info/WHEEL
suplex-0.2.6.dist-info/RECORD
