Metadata-Version: 2.4
Name: suplex
Version: 0.2.6
Summary: A Python library for interacting with Supabase REST API in Reflex applications
Project-URL: Homepage, https://github.com/hjpr/suplex
Project-URL: Bug Tracker, https://github.com/hjpr/suplex/issues
Author-email: Jeremy Medlin <jeremy.f.medlin@gmail.com>
License: MIT
Keywords: authentication,database,reflex,supabase
Classifier: Development Status :: 3 - Alpha
Classifier: Intended Audience :: Developers
Classifier: Programming Language :: Python :: 3
Classifier: Programming Language :: Python :: 3.12
Requires-Python: >=3.12
Requires-Dist: dotenv>=0.9.9
Requires-Dist: httpx>=0.24.0
Requires-Dist: pyjwt>=2.10.1
Requires-Dist: reflex>=0.8.0
Requires-Dist: rich>=13.9.4
